ugbio_omics/__init__.py
ugbio_omics/compare_cromwell_omics.py
ugbio_omics/compare_omics_runs.py
ugbio_omics/cost_distribution_by_version.py
ugbio_omics/cromwell_calculate_cost.py
ugbio_omics/db_access.py
ugbio_omics/get_omics_log.py
ugbio_omics/get_performance.py
ugbio_omics/get_run_cost.py
ugbio_omics/get_run_info.py
ugbio_omics/omics_cache_path.py
ugbio_omics/parse_manifest_log.py
ugbio_omics/report_missing_runs.py
ugbio_omics/report_run_completion.py
ugbio_omics/retrieve_from_glacier.py
ugbio_omics-1.20.0.dist-info/METADATA
ugbio_omics-1.20.0.dist-info/WHEEL
ugbio_omics-1.20.0.dist-info/entry_points.txt
ugbio_omics-1.20.0.dist-info/top_level.txt
ugbio_omics-1.20.0.dist-info/RECORD
