Metadata-Version: 2.4
Name: ugbio_omics
Version: 1.20.0
Summary: Ultima Genomics bioinfo utils for working with AWS Health-Omics
Author-email: Inbal Zelig <inbal.zelig@ultimagen.com>
Requires-Python: >=3.11
Requires-Dist: plotly>=5.23.0
Requires-Dist: google-cloud-storage>=2.19.0
Requires-Dist: boto3>=1.35.69
Requires-Dist: pandas<3.0.0,>=2.2.3
Requires-Dist: winval>=0.7.5
Provides-Extra: db
Requires-Dist: pandas[hdf5]>=2.2.2; extra == "db"
Requires-Dist: pymongo>=4.11.1; extra == "db"
